odoo/addons/stock_dangerous_goods/README.rst
odoo/addons/stock_dangerous_goods/__init__.py
odoo/addons/stock_dangerous_goods/__manifest__.py
odoo/addons/stock_dangerous_goods/i18n/it.po
odoo/addons/stock_dangerous_goods/i18n/nl.po
odoo/addons/stock_dangerous_goods/i18n/pt.po
odoo/addons/stock_dangerous_goods/i18n/pt_BR.po
odoo/addons/stock_dangerous_goods/i18n/stock_dangerous_goods.pot
odoo/addons/stock_dangerous_goods/models/__init__.py
odoo/addons/stock_dangerous_goods/models/product_product.py
odoo/addons/stock_dangerous_goods/models/stock_move_line.py
odoo/addons/stock_dangerous_goods/models/stock_quant_package.py
odoo/addons/stock_dangerous_goods/readme/CONTRIBUTORS.md
odoo/addons/stock_dangerous_goods/readme/CREDITS.md
odoo/addons/stock_dangerous_goods/readme/DESCRIPTION.md
odoo/addons/stock_dangerous_goods/static/description/icon.png
odoo/addons/stock_dangerous_goods/static/description/index.html
odoo/addons/stock_dangerous_goods/tests/__init__.py
odoo/addons/stock_dangerous_goods/tests/test_has_lq_products.py
odoo_addon_stock_dangerous_goods-18.0.1.0.0.9.dist-info/METADATA
odoo_addon_stock_dangerous_goods-18.0.1.0.0.9.dist-info/WHEEL
odoo_addon_stock_dangerous_goods-18.0.1.0.0.9.dist-info/top_level.txt
odoo_addon_stock_dangerous_goods-18.0.1.0.0.9.dist-info/RECORD
