Metadata-Version: 2.1
Name: odoo-addon-stock_dangerous_goods
Version: 18.0.1.0.0.9
Requires-Python: >=3.10
Requires-Dist: odoo-addon-l10n_eu_product_adr_dangerous_goods==18.0.*
Requires-Dist: odoo==18.0.*
Summary: Adds utility fields to manage dangerous goods
Home-page: https://github.com/OCA/stock-logistics-workflow
License: AGPL-3
Author: Camptocamp SA, Odoo Community Association (OCA)
Author-email: support@odoo-community.org
Classifier: Programming Language :: Python
Classifier: Framework :: Odoo
Classifier: Framework :: Odoo :: 18.0
Classifier: License :: OSI Approved :: GNU Affero General Public License v3
